git_idiff/__init__.py
git_idiff/__main__.py
git_idiff/gitdiff.py
git_idiff/overload.py
git_idiff/ui/__init__.py
git_idiff/ui/colors.py
git_idiff/ui/cui.py
git_idiff/ui/diff.py
git_idiff/ui/filelist.py
git_idiff/ui/loader.py
git_idiff/ui/messagebox.py
git_idiff/ui/pad.py
git_idiff/ui/statusbar.py
git_idiff/ui/utils.py
git_idiff/ui/vector.py
git_idiff-0.0.1.dist-info/LICENSE
git_idiff-0.0.1.dist-info/METADATA
git_idiff-0.0.1.dist-info/WHEEL
git_idiff-0.0.1.dist-info/entry_points.txt
git_idiff-0.0.1.dist-info/top_level.txt
git_idiff-0.0.1.dist-info/RECORD
