Metadata-Version: 2.1
Name: git-idiff
Version: 0.0.1
Summary: An interactive curses tool for viewing git diffs that span multiple files.
Home-page: https://github.com/WiLGYSeF/git-idiff
Author: wilgysef
Author-email: wilgysef@gmail.com
License: UNKNOWN
Project-URL: Bug Tracker, https://github.com/WiLGYSeF/git-idiff/issues
Platform: UNKNOWN
Classifier: Programming Language :: Python :: 3
Classifier: License :: OSI Approved :: MIT License
Classifier: Operating System :: OS Independent
Requires-Python: >=3.6
License-File: LICENSE
